{
  "hash": "69b8e0a4",
  "configHash": "b76ed1ac",
  "lockfileHash": "39b28f53",
  "browserHash": "99bcfbb7",
  "optimized": {
    "vue": {
      "src": "../../../node_modules/vue/dist/vue.runtime.esm-bundler.js",
      "file": "vue.js",
      "fileHash": "6423bb2b",
      "needsInterop": false
    },
    "vitepress > @vue/devtools-api": {
      "src": "../../../node_modules/@vue/devtools-api/dist/index.js",
      "file": "vitepress___@vue_devtools-api.js",
      "fileHash": "97453922",
      "needsInterop": false
    },
    "vitepress > @vueuse/core": {
      "src": "../../../node_modules/@vueuse/core/index.mjs",
      "file": "vitepress___@vueuse_core.js",
      "fileHash": "77125ba0",
      "needsInterop": false
    },
    "@theme/index": {
      "src": "../../../node_modules/vitepress/dist/client/theme-default/index.js",
      "file": "@theme_index.js",
      "fileHash": "4d9197cb",
      "needsInterop": false
    }
  },
  "chunks": {
    "chunk-WZSWIX5T": {
      "file": "chunk-WZSWIX5T.js"
    },
    "chunk-Z6B2QTD3": {
      "file": "chunk-Z6B2QTD3.js"
    }
  }
}